{
  "budget_id": "BUD-2024-001",
  "client_metadata": {
    "name": "Acme España S.L.",
    "sector": "saas",
    "country": "ES"
  },
  "project_summary": "B2B SaaS platform with Workday integration",
  "main_technology": "nodejs",
  "year": 2024,
  "total_estimated_hours": 320,
  "components": [
    {
      "component_id": "DISC-001",
      "name": "Discovery phase",
      "description": "Requirements gathering and analysis",
      "tech_stack": ["nodejs", "react", "postgresql"],
      "estimated_hours": 40,
      "complexity": "medium",
      "dependencies": []
    },
    {
      "component_id": "UX-001",
      "name": "UX Design",
      "description": "User interface and experience design",
      "tech_stack": ["figma", "react"],
      "estimated_hours": 60,
      "complexity": "medium",
      "dependencies": ["DISC-001"]
    },
    {
      "component_id": "IMPL-001",
      "name": "MVP Implementation",
      "description": "Core functionality implementation",
      "tech_stack": ["nodejs", "express", "postgresql", "react"],
      "estimated_hours": 160,
      "complexity": "high",
      "dependencies": ["UX-001"]
    },
    {
      "component_id": "QA-001",
      "name": "QA and Testing",
      "description": "Testing and quality assurance",
      "tech_stack": ["jest", "cypress"],
      "estimated_hours": 60,
      "complexity": "medium",
      "dependencies": ["IMPL-001"]
    }
  ]
}
